{
	"accounts payable": 1,
	"accounts receivable": 1,
	"assets": 1,
	"audit": 1,
	"benefit analysis": 1,
	"bid/ask": 1,
	"bonds": 1,
	"branch operations": 1,
	"calculation": 1,
	"capital": 1,
	"collections": 1,
	"commercial banking": 1,
	"consumer": 1,
	"corporate tax": 1,
	"cost accounting": 1,
	"cost analysis": 1,
	"credit analysis": 1,
	"debt financing": 1,
	"deposit": 1,
	"e-trade": 1,
	"excel": 1,
	"filo": 1,
	"financial analysis": 1,
	"financial planning": 1,
	"foreign exchange": 1,
	"global banking": 1,
	"international financing": 1,
	"investment": 1,
	"investor relations": 1,
	"job costing": 1,
	"letters of credit": 1,
	"leveraged buyout": 1,
	"loan": 1,
	"loss": 1,
	"numbers": 1,
	"operating budgets": 1,
	"portfolio": 1,
	"profits": 1,
	"recovery": 1,
	"return on equity": 1,
	"return on investment": 1,
	"revenue": 1,
	"risk management": 1,
	"securities": 1,
	"shareholder": 1,
	"spreadsheet": 1,
	"stock": 1,
	"trade": 1,
	"treasury": 1,
	"trust": 1,
	"turnaround": 1

}